FINALPROJECT/__init__.py
FINALPROJECT/__main__.py
btceth_manager-1.0.0.dist-info/METADATA
btceth_manager-1.0.0.dist-info/WHEEL
btceth_manager-1.0.0.dist-info/top_level.txt
btceth_manager-1.0.0.dist-info/RECORD
