Metadata-Version: 2.1
Name: btceth-manager
Version: 1.0.0
Summary: For personal use
Home-page: UNKNOWN
Author: robin9634
Author-email: justforad9634@gmail.com
License: UNKNOWN
Platform: UNKNOWN
Classifier: Programming Language :: Python :: 3
Classifier: License :: OSI Approved :: MIT License
Classifier: Operating System :: OS Independent
Requires-Python: >=3.6
